zfspace/__init__.py
zfspace/__main__.py
zfspace/zfspace.py
zfspace-0.7.6.dist-info/METADATA
zfspace-0.7.6.dist-info/WHEEL
zfspace-0.7.6.dist-info/entry_points.txt
zfspace-0.7.6.dist-info/license_files/LICENSE
zfspace-0.7.6.dist-info/RECORD
